{
  "persons": [
    {
      "vader": {
        "value": "Jacobus",
        "cell": "c_86"
      },
      "moeder": {
        "value": "Catharina Ballert",
        "cell": "c_86"
      },
      "geboorte_datum": {
        "value": "9 October 1775",
        "cell": "c_86"
      },
      "geboorte_plaats": {
        "value": "Schoonhoven",
        "cell": "c_86"
      },
      "laatste_woonplaats": {
        "value": "Bruille",
        "cell": "c_86"
      }
    },
    {
      "vader": {
        "value": "Coert Hendrik",
        "cell": "c_818"
      },
      "moeder": {
        "value": "Maria Van Onbeek",
        "cell": "c_818"
      },
      "geboorte_datum": {
        "value": "23 december 1771",
        "cell": "c_818"
      },
      "geboorte_plaats": {
        "value": "S'Hage",
        "cell": "c_818"
      },
      "laatste_woonplaats": {
        "value": "S'Hage",
        "cell": "c_818"
      }
    }
  ]
}